README.rst
setup.py
papernetwork/__init__.py
papernetwork/core.py
papernetwork.egg-info/PKG-INFO
papernetwork.egg-info/SOURCES.txt
papernetwork.egg-info/dependency_links.txt
papernetwork.egg-info/requires.txt
papernetwork.egg-info/top_level.txt