Metadata-Version: 1.1
Name: papernetwork
Version: 0.1.2
Summary: Collect and analyze scientific literature from Semantic Scholar
Home-page: https://github.com/EvdH0/papernetwork
Author: Eric van der Helm
Author-email: i@iric.nl
License: MIT
Platform: UNKNOWN
Classifier: Development Status :: 2 - Pre-Alpha
Classifier: License :: OSI Approved :: MIT License
Classifier: Programming Language :: Python :: 3.6
Classifier: Programming Language :: Python :: 3.7
Classifier: Programming Language :: Python :: 3.8
